multi_cube/__init__.py
multi_cube/config/config.yaml
multi_cube/scripts/__init__.py
multi_cube/scripts/makecube.py
multi_cube/scripts/modules/__init__.py
multi_cube/scripts/modules/bash_utils.py
multi_cube/scripts/modules/casa_imcontsub.py
multi_cube/scripts/modules/casa_utils.py
multi_cube/scripts/modules/cleanup_utils.py
multi_cube/scripts/modules/config_utils.py
multi_cube/scripts/modules/mstransform_utils.py
multi_cube/scripts/modules/remove_unwanted.py
multi_cube/scripts/modules/setup_utils.py
multi_cube/scripts/modules/stack_fits.py
multi_cube/scripts/modules/wsclean_utils.py
multi_cube-0.5.2.dist-info/METADATA
multi_cube-0.5.2.dist-info/WHEEL
multi_cube-0.5.2.dist-info/entry_points.txt
multi_cube-0.5.2.dist-info/top_level.txt
multi_cube-0.5.2.dist-info/RECORD
