Metadata-Version: 2.1
Name: multi-cube
Version: 0.5.2
Summary: A convenience tool that orchestrates the parallel generation of FITS cubes from a continuum-subtracted ms file.
Home-page: https://github.com/LeonMtshweni/multi-cube
Author: Leon K.B. Mtshweni
Author-email: leonkb.m.astro@gmail.com
Classifier: Programming Language :: Python :: 3
Classifier: License :: OSI Approved :: MIT License
Classifier: Operating System :: OS Independent
Requires-Python: >=3.8
Requires-Dist: PyYAML >=6.0.1
